{
    "openrpc": "1.2.4",
    "info": {
        "title": "Privacy",
        "description": "A module for managing device settings.",
        "version": "0.0.0"
    },
    "methods": [
        {
            "name": "allowAppDataCollection",
            "tags": [
                {
                    "name": "property",
                    "x-allow-value": true
                },
                {
                    "name": "capabilities",
                    "x-manages": [
                        "xrn:firebolt:capability:privacy:settings"
                    ]
                }
            ],
            "summary": "Whether the user allows a certain app to send any data and be collected",
            "params": [
                {
                    "name": "appId",
                    "required": true,
                    "schema": {
                        "type": "string"
                    }
                }
            ],
            "result": {
                "name": "allow",
                "schema": {
                    "type": "boolean"
                }
            },
            "examples": [
                {
                    "name": "Default Example",
                    "params": [
                        {
                            "name": "appId",
                            "value": "some-app"
                        }
                    ],
                    "result": {
                        "name": "allow",
                        "value": true
                    }
                }
            ]
        },
        {
            "name": "allowAppEntitlementCollection",
            "tags": [
                {
                    "name": "property"
                },
                {
                    "name": "capabilities",
                    "x-manages": [
                        "xrn:firebolt:capability:privacy:settings"
                    ]
                }
            ],
            "summary": "Whether the user allows a certain app to shared entitlements",
            "params": [
                {
                    "name": "appId",
                    "required": true,
                    "schema": {
                        "type": "string"
                    }
                }
            ],
            "result": {
                "name": "allow",
                "schema": {
                    "type": "boolean"
                }
            },
            "examples": [
                {
                    "name": "Default Example",
                    "params": [
                        {
                            "name": "appId",
                            "value": "some-app"
                        }
                    ],
                    "result": {
                        "name": "allow",
                        "value": true
                    }
                }
            ]
        },
        {
            "name": "allowResumePoints",
            "tags": [
                {
                    "name": "property"
                },
                {
                    "name": "capabilities",
                    "x-manages": [
                        "xrn:firebolt:capability:privacy:settings"
                    ]
                }
            ],
            "summary": "Whether the user allows resume points for content to show in the main experience",
            "params": [
            ],
            "result": {
                "name": "allow",
                "schema": {
                    "type": "boolean"
                }
            },
            "examples": [
                {
                    "name": "Default Example",
                    "params": [
                    ],
                    "result": {
                        "name": "allow",
                        "value": true
                    }
                }
            ]
        },
        {
            "name": "allowUnentitledResumePoints",
            "tags": [
                {
                    "name": "property"
                },
                {
                    "name": "capabilities",
                    "x-manages": [
                        "xrn:firebolt:capability:privacy:settings"
                    ]
                }
            ],
            "summary": "Whether the user allows resume points for content from unentitled providers to show in the main experience",
            "params": [
            ],
            "result": {
                "name": "allow",
                "schema": {
                    "type": "boolean"
                }
            },
            "examples": [
                {
                    "name": "Default Example",
                    "params": [
                    ],
                    "result": {
                        "name": "allow",
                        "value": true
                    }
                }
            ]
        },
        {
            "name": "allowWatchHistory",
            "tags": [
                {
                    "name": "property"
                },
                {
                    "name": "capabilities",
                    "x-manages": [
                        "xrn:firebolt:capability:privacy:settings"
                    ]
                }
            ],
            "summary": "Whether the user allows their watch history from all sources to show in the main experience",
            "params": [
            ],
            "result": {
                "name": "allow",
                "schema": {
                    "type": "boolean"
                }
            },
            "examples": [
                {
                    "name": "Default Example",
                    "params": [
                    ],
                    "result": {
                        "name": "allow",
                        "value": true
                    }
                }
            ]
        },
        {
            "name": "allowProductAnalytics",
            "tags": [
                {
                    "name": "property"
                },
                {
                    "name": "capabilities",
                    "x-manages": [
                        "xrn:firebolt:capability:privacy:settings"
                    ]
                }
            ],
            "summary": "Whether the user allows their usage data can be used for analytics about the product",
            "params": [
            ],
            "result": {
                "name": "allow",
                "schema": {
                    "type": "boolean"
                }
            },
            "examples": [
                {
                    "name": "Default Example",
                    "params": [
                    ],
                    "result": {
                        "name": "allow",
                        "value": true
                    }
                }
            ]
        },
        {
            "name": "allowPersonalization",
            "tags": [
                {
                    "name": "property"
                },
                {
                    "name": "capabilities",
                    "x-manages": [
                        "xrn:firebolt:capability:privacy:settings"
                    ]
                }
            ],
            "summary": "Whether the user allows their usage data to be used for personalization and recommendations",
            "params": [
            ],
            "result": {
                "name": "allow",
                "schema": {
                    "type": "boolean"
                }
            },
            "examples": [
                {
                    "name": "Default Example",
                    "params": [
                    ],
                    "result": {
                        "name": "allow",
                        "value": true
                    }
                }
            ]
        },
        {
            "name": "allowUnentitledPersonalization",
            "tags": [
                {
                    "name": "property"
                },
                {
                    "name": "capabilities",
                    "x-manages": [
                        "xrn:firebolt:capability:privacy:settings"
                    ]
                }
            ],
            "summary": "Whether the user allows their usage data to be used for personalization and recommendations for unentitled content",
            "params": [
            ],
            "result": {
                "name": "allow",
                "schema": {
                    "type": "boolean"
                }
            },
            "examples": [
                {
                    "name": "Default Example",
                    "params": [
                    ],
                    "result": {
                        "name": "allow",
                        "value": true
                    }
                }
            ]
        },
        {
            "name": "allowRemoteDiagnostics",
            "tags": [
                {
                    "name": "property"
                },
                {
                    "name": "capabilities",
                    "x-manages": [
                        "xrn:firebolt:capability:privacy:settings"
                    ]
                }
            ],
            "summary": "Whether the user allows their personal data to be included in diagnostic telemetry. This also allows whether device logs can be remotely accessed from the client device",
            "params": [
            ],
            "result": {
                "name": "allow",
                "schema": {
                    "type": "boolean"
                }
            },
            "examples": [
                {
                    "name": "Default Example",
                    "params": [
                    ],
                    "result": {
                        "name": "allow",
                        "value": true
                    }
                }
            ]
        },
        {
            "name": "allowPrimaryContentAdTargeting",
            "tags": [
                {
                    "name": "property"
                },
                {
                    "name": "capabilities",
                    "x-manages": [
                        "xrn:firebolt:capability:privacy:settings"
                    ]
                }
            ],
            "summary": "Whether the user allows ads to be targeted to the user while watching content in the primary experience",
            "params": [
            ],
            "result": {
                "name": "allow",
                "schema": {
                    "type": "boolean"
                }
            },
            "examples": [
                {
                    "name": "Default Example",
                    "params": [
                    ],
                    "result": {
                        "name": "allow",
                        "value": true
                    }
                }
            ]
        },
        {
            "name": "allowPrimaryBrowseAdTargeting",
            "tags": [
                {
                    "name": "property"
                },
                {
                    "name": "capabilities",
                    "x-manages": [
                        "xrn:firebolt:capability:privacy:settings"
                    ]
                }
            ],
            "summary": "Whether the user allows ads to be targeted to the user while browsing in the primary experience",
            "params": [
            ],
            "result": {
                "name": "allow",
                "schema": {
                    "type": "boolean"
                }
            },
            "examples": [
                {
                    "name": "Default Example",
                    "params": [
                    ],
                    "result": {
                        "name": "allow",
                        "value": true
                    }
                }
            ]
        },
        {
            "name": "allowAppContentAdTargeting",
            "tags": [
                {
                    "name": "property"
                },
                {
                    "name": "capabilities",
                    "x-manages": [
                        "xrn:firebolt:capability:privacy:settings"
                    ]
                }
            ],
            "summary": "Whether the user allows ads to be targeted to the user while watching content in apps",
            "params": [
            ],
            "result": {
                "name": "allow",
                "schema": {
                    "type": "boolean"
                }
            },
            "examples": [
                {
                    "name": "Default Example",
                    "params": [
                    ],
                    "result": {
                        "name": "allow",
                        "value": true
                    }
                }
            ]
        },
        {
            "name": "allowACRCollection",
            "tags": [
                {
                    "name": "property"
                },
                {
                    "name": "capabilities",
                    "x-manages": [
                        "xrn:firebolt:capability:privacy:settings"
                    ]
                }
            ],
            "summary": "Whether the user allows their automatic content recognition data to be collected",
            "params": [
            ],
            "result": {
                "name": "allow",
                "schema": {
                    "type": "boolean"
                }
            },
            "examples": [
                {
                    "name": "Default Example",
                    "params": [
                    ],
                    "result": {
                        "name": "allow",
                        "value": true
                    }
                }
            ]
        },
        {
            "name": "allowCameraAnalytics",
            "tags": [
                {
                    "name": "property"
                },
                {
                    "name": "capabilities",
                    "x-manages": [
                        "xrn:firebolt:capability:privacy:settings"
                    ]
                }
            ],
            "summary": "Whether the user allows data from their camera to be used for Product Analytics",
            "params": [
            ],
            "result": {
                "name": "allow",
                "schema": {
                    "type": "boolean"
                }
            },
            "examples": [
                {
                    "name": "Default Example",
                    "params": [
                    ],
                    "result": {
                        "name": "allow",
                        "value": true
                    }
                }
            ]
        }
   ],
    "components": {
        "schemas": {
        }
    }
}